towhee/models/README.md
towhee/models/README_CN.md
towhee/models/__init__.py
towhee/models/acar_net/__init__.py
towhee/models/acar_net/backbone.py
towhee/models/acar_net/head.py
towhee/models/acar_net/model.py
towhee/models/acar_net/neck.py
towhee/models/acar_net/utils.py
towhee/models/action_clip/__init__.py
towhee/models/action_clip/action_clip.py
towhee/models/action_clip/action_clip_utils.py
towhee/models/action_clip/text_prompt.py
towhee/models/action_clip/visual_prompt.py
towhee/models/allinone/__init__.py
towhee/models/allinone/allinone.py
towhee/models/bridgeformer/__init__.py
towhee/models/bridgeformer/bridge_former.py
towhee/models/bridgeformer/bridge_former_training.py
towhee/models/bridgeformer/bridge_former_training_block.py
towhee/models/clip/README.md
towhee/models/clip/__init__.py
towhee/models/clip/auxilary.py
towhee/models/clip/bpe_simple_vocab_16e6.txt.gz
towhee/models/clip/clip.py
towhee/models/clip/clip_utils.py
towhee/models/clip/simple_tokenizer.py
towhee/models/clip4clip/__init__.py
towhee/models/clip4clip/clip4clip.py
towhee/models/clip4clip/until_module.py
towhee/models/clip4clip/utils.py
towhee/models/coca/__init__.py
towhee/models/coca/coca.py
towhee/models/coformer/__init__.py
towhee/models/coformer/backbone.py
towhee/models/coformer/coformer.py
towhee/models/coformer/config.py
towhee/models/coformer/transformer.py
towhee/models/coformer/utils.py
towhee/models/collaborative_experts/__init__.py
towhee/models/collaborative_experts/collaborative_experts.py
towhee/models/collaborative_experts/net_vlad.py
towhee/models/collaborative_experts/util.py
towhee/models/convnext/__init__.py
towhee/models/convnext/configs.py
towhee/models/convnext/convnext.py
towhee/models/convnext/utils.py
towhee/models/cvnet/__init__.py
towhee/models/cvnet/cvnet.py
towhee/models/cvnet/cvnet_block.py
towhee/models/cvnet/cvnet_utils.py
towhee/models/cvnet/resnet.py
towhee/models/drl/__init__.py
towhee/models/drl/drl.py
towhee/models/drl/module_cross.py
towhee.models-1.1.3.dist-info/LICENSE
towhee.models-1.1.3.dist-info/METADATA
towhee.models-1.1.3.dist-info/WHEEL
towhee.models-1.1.3.dist-info/entry_points.txt
towhee.models-1.1.3.dist-info/top_level.txt
towhee.models-1.1.3.dist-info/RECORD
